smart/MNN.py
smart/__init__.py
smart/build_graph.py
smart/layer.py
smart/model.py
smart/train.py
smart/utils.py
bio_smart-0.1.2.dist-info/METADATA
bio_smart-0.1.2.dist-info/WHEEL
bio_smart-0.1.2.dist-info/top_level.txt
bio_smart-0.1.2.dist-info/RECORD
