Metadata-Version: 2.4
Name: bio-SMART
Version: 0.1.2
Summary: SMART: Spatial multi-omic aggregation using graph neural networks and metric learning
Author-email: Chen Qiyi <2210274047@email.szu.edu.cn>
License: MIT
Project-URL: Homepage, https://github.com/ws6tg/SMART-main
Project-URL: Documentation, https://smart-tutorials.readthedocs.io
Project-URL: Issues, https://github.com/ws6tg/SMART-main/issues
Requires-Python: >=3.9
Requires-Dist: muon==0.1.6
Requires-Dist: scanpy==1.10.2
Requires-Dist: scikit-learn==1.5.1
Requires-Dist: anndata==0.10.8
Requires-Dist: matplotlib==3.9.2
Requires-Dist: tqdm==4.66.5
Requires-Dist: numba==0.60.0
Requires-Dist: rpy2==3.5.12
Requires-Dist: torch==2.4.1
Requires-Dist: torch_geometric==2.3.0
Requires-Dist: harmony-pytorch==0.1.8
Requires-Dist: scikit-misc==0.3.1
